rhumba
examples
twisted
