Metadata-Version: 1.1
Name: rhumba
Version: 0.1.17
Summary: An asynchronous job queue written in Twisted
Home-page: http://github.com/calston/rhumba
Author: Colin Alston
Author-email: colin.alston@gmail.com
License: MIT
Platform: UNKNOWN
Classifier: Development Status :: 4 - Beta
Classifier: Intended Audience :: System Administrators
Classifier: License :: OSI Approved :: MIT License
Classifier: Operating System :: POSIX
Classifier: Programming Language :: Python
Classifier: Topic :: System :: Distributed Computing
